[{"title":"","body":"Beautiful","rating":"5","review_date":"6/4/2019 0:00","source":"aliexpress","curated":"ok","reviewer_name":"Sukree Sachamuniwongse","reviewer_email":"sukree_is@hotmail.com","product_id":"","product_handle":"we-are-the-champions-limited-edition-keychain-for-liverpool-fans","reply":"","reply_date":"","picture_urls":"","ip_address":"","location":"","metaobject_handle":"","body_ar":"جميل","body_zh_TW":"美麗的","body_cs":"Krásný","body_da":"Smuk","body_nl":"Mooi","body_fi":"Kaunis","body_fr":"Beau","body_de":"Schön","body_el":"Ομορφος","body_he":"יָפֶה","body_it":"Bellissimo","body_ja":"美しい","body_ko":"아름다운","body_ms":"Cantik","body_no":"Vakker","body_pl":"Piękny","body_pt":"Lindo","body_es":"Hermoso","body_sv":"Vacker","body_th":"สวย","status":"","user_identifier":""},{"title":"","body":"Fantastic!","rating":"5","review_date":"6/4/2019 0:00","source":"aliexpress","curated":"ok","reviewer_name":"Tikky Stingray","reviewer_email":"sukree_is@hotmail.com","product_id":"","product_handle":"we-are-the-champions-limited-edition-keychain-for-liverpool-fans","reply":"","reply_date":"","picture_urls":"","ip_address":"","location":"","metaobject_handle":"","body_ar":"رائع!","body_zh_TW":"極好的！","body_cs":"Fantastický!","body_da":"Fantastisk!","body_nl":"Fantastisch!","body_fi":"Fantastinen!","body_fr":"Fantastique!","body_de":"Fantastisch!","body_el":"Φανταστικός!","body_he":"פַנטַסטִי!","body_it":"Fantastico!","body_ja":"素晴らしい！","body_ko":"환상적이에요!","body_ms":"Hebat!","body_no":"Fantastisk!","body_pl":"Fantastyczny!","body_pt":"Fantástico!","body_es":"¡Fantástico!","body_sv":"Fantastisk!","body_th":"มหัศจรรย์!","status":"","user_identifier":""}]